[
    {
        "id": 1,
        "food": "Pizza",
        "provider": "PACS",
        "provider-full-name": "Practical Applications of Computer Science",
        "location": "DCC 709",
        "time": "4:00 PM",
        "stock": 5,
        "availability": "until 6:00 PM",
        "description": "There are 5 pizzas, vegetarian and meat options available. All Halal.",
        "vegan": false,
        "vegetarian": true,
        "halal": true,
        "dairyFree": false,
        "glutenFree": false,
        "peanutFree": true,
        "beef": true,
        "chicken": true,
        "pork": false,
        "fish": false,
        "shelfish": false,
        "otherMeat": false
    },
    {
        "id": 2,
        "food": "Wraps",
        "provider": "VIRO",
        "provider-full-name": "VIRO",
        "location": "DCC 709",
        "time": "4:00 PM",
        "stock": 25,
        "availability": "until 6:00 PM",
        "description": "There are 25 wraps, chicken and beef options available. All Halal.",
        "vegan": false,
        "vegetarian": false,
        "halal": true,
        "dairyFree": true,
        "glutenFree": false,
        "peanutFree": true,
        "beef": true,
        "chicken": true,
        "pork": false,
        "fish": false,
        "shelfish": false,
        "otherMeat": false
    }
]